{
    "name": "My Server",
    "host": "iad1-shared-b7-21.dreamhost.com",
    "protocol": "sftp",
    "port": 22,
    "username": "dh_wkair2",
    "remotePath": "/home/dh_wkair2/mission-pure.com",
    "uploadOnSave": false,
    "downloadOnOpen": false,
    "useTempFile": false,
    "openSsh": false,
    "interactiveAuth": false,
    "secure": false,
    "remoteTimeOffsetInHours": 0,
    "connectTimeout": 60000,
    "concurrency": 1,
    "watcher": {
        "files": "**/*",
        "autoUpload": false,
        "autoDelete": false
    },
    "ignore": [
        ".vscode/**",
        "scripts/**",
        "package.json",
        "server.js",
        "data/ZIP_COUNTY_122025.xlsx"
    ]
}
